chronos.py
chronos_plotting.py
chronos_utils.py
chronos_forecast-0.1.0.dist-info/LICENSE
chronos_forecast-0.1.0.dist-info/METADATA
chronos_forecast-0.1.0.dist-info/WHEEL
chronos_forecast-0.1.0.dist-info/top_level.txt
chronos_forecast-0.1.0.dist-info/RECORD
