Metadata-Version: 2.1
Name: chronos-forecast
Version: 0.1.0
Summary: Time series prediction using probabilistic programming
Home-page: https://github.com/boris-shabash/Chronos
Author: Boris Shabash
Author-email: boris.shabash@gmail.com
License: MIT
Platform: UNKNOWN
Classifier: Programming Language :: Python :: 3
Classifier: Programming Language :: Python :: 3.7
Classifier: Programming Language :: Python :: 3.8
Classifier: Topic :: Scientific/Engineering :: Artificial Intelligence
Classifier: License :: OSI Approved :: MIT License
Classifier: Operating System :: OS Independent
Requires-Python: >=3.7
Requires-Dist: pandas (>=1.1)
Requires-Dist: numpy (>=1.19)
Requires-Dist: matplotlib (>=3.2)
Requires-Dist: torch (>=1.5)
Requires-Dist: pyro-ppl (>=1.3)
Provides-Extra: dev
Requires-Dist: pytest (==6.2.1) ; extra == 'dev'
